freshdesk/__init__.py
freshdesk/create_new_post_shell.py
freshdesk/deploy.py
freshdesk/track_changes.py
freshdesk/use_deploy.py
freshdesk/API/__init__.py
freshdesk/API/freshdesk.py
freshdesk/scripts/__init__.py
freshdesk/scripts/cloudfront_images.py
freshdesk/scripts/compare_repos.py
freshdesk/scripts/file_constants.py
freshdesk/scripts/get_articles.py
freshdesk/scripts/get_images.py
freshdesk/scripts/renderer.py
freshdesk/scripts/startup_changes.py
freshdesk/scripts/timing.py
freshdesk_help_center_backer-0.1.1.dist-info/DESCRIPTION.rst
freshdesk_help_center_backer-0.1.1.dist-info/METADATA
freshdesk_help_center_backer-0.1.1.dist-info/RECORD
freshdesk_help_center_backer-0.1.1.dist-info/WHEEL
freshdesk_help_center_backer-0.1.1.dist-info/entry_points.txt
freshdesk_help_center_backer-0.1.1.dist-info/metadata.json
freshdesk_help_center_backer-0.1.1.dist-info/top_level.txt
