Metadata-Version: 2.0
Name: freshdesk-help-center-backer
Version: 0.1.1
Summary: A Freshdesk help center backer written in Python
Home-page: https://github.com/aerofs/freshdesk-help-center-backer
Author: AeroFS
Author-email: oss@aerofs.com
License: UNKNOWN
Keywords: freshdesk,solution,help center,knowledge base
Platform: UNKNOWN
Classifier: Development Status :: 3 - Alpha
Classifier: Intended Audience :: Developers
Classifier: License :: OSI Approved :: MIT License
Classifier: Natural Language :: English
Classifier: Programming Language :: Python
Classifier: Topic :: Software Development
Requires-Dist: boto
Requires-Dist: colorama
Requires-Dist: requests
Requires-Dist: watchdog
